Metadata-Version: 1.0
Name: bin-distr-christoph2845
Version: 0.1
Summary: Test package binomial distribution
Home-page: UNKNOWN
Author: UNKNOWN
Author-email: UNKNOWN
License: UNKNOWN
Platform: UNKNOWN
